{"card_name": "We Can't Give Up!", "color": "B", "rarity": "common", "type": "Sorcery", "number": 114, "color_identity": "B", "cost": "{4}{B}", "rules_text": "This spell costs {1} less to cast for each creature in your sentai. [i](A sentai is up to one creature of each color.)[/i]\nReturn up to two target creature cards from your graveyard to your hand.", "flavor_text": "[i][/i]", "pt": "", "special_text": "", "shape": "normal", "set": "PRISM", "loyalty": "", "artist": "Yingyi Xsu", "notes": "Return creature", "image_type": "jpg"}