{"card_name": "Croissant Crabs", "color": "G", "rarity": "uncommon", "type": "Sorcery", "number": 157, "color_identity": "G", "cost": "{X}{G}{G}", "rules_text": "Create three Food tokens. Then choose up to X noncreature artifacts you control. Those artifacts become 2/2 blue Crab Minion creatures in addition to their other types.", "flavor_text": "[i][/i]", "pt": "", "special_text": "", "shape": "normal", "set": "PRISM", "loyalty": "", "artist": "Juan Diego Leon", "notes": "", "image_type": "jpg"}