{"card_name": "Hero Twins", "color": "G", "rarity": "mythic", "type": "Creature \u2013 Human Warrior", "number": 164, "color_identity": "G", "cost": "{3}{G}{G}", "rules_text": "When you cast Hero Twins, copy it.\nAt the beginning of your upkeep, if you don't control another creature named Hero Twins, create a token that's a copy of Hero Twins.", "flavor_text": "[i][/i]", "pt": "4/3", "special_text": "", "shape": "normal", "set": "PRISM", "loyalty": "", "artist": "\u4e5d\u65e5\u4e5d\u53f7/ jiur", "notes": "", "image_type": "jpg"}