{"card_name": "Lantalian Princess", "color": "U", "rarity": "common", "type": "Creature \u2013 Merfolk Noble", "number": 60, "color_identity": "U", "cost": "{1}{U}", "rules_text": "When Lantalian Princess enters, look at the top four cards of your library. You may reveal an artifact, Island, or Demiplane card from among them and put it into your hand. Put the rest on the bottom of your library in any order.", "flavor_text": "[i][/i]", "pt": "2/1", "special_text": "", "shape": "normal", "set": "PRISM", "loyalty": "", "artist": "viki-vaki", "notes": "SMALL creature CMC 2", "image_type": "jpg"}