{"card_name": "Impulsive Underling", "color": "R", "rarity": "rare", "type": "Creature \u2013 Demon Warrior", "number": 108, "color_identity": "R", "cost": "{R}", "rules_text": "[i]Damned[/i] \u2013 Whenever this creature attacks, put a +1/+1 counter on this creature if you sacrificed a permanent this turn.\nWhen this creature dies, it deals damage equal to its power to each opponent.", "flavor_text": "[i][/i]", "pt": "1/1", "special_text": "", "shape": "normal", "set": "KDT", "loyalty": "", "artist": "Lightwing Academy", "notes": "", "image_type": "jpg"}