{"card_name": "Distinguished Weaverkin", "color": "G", "rarity": "uncommon", "type": "Creature \u2013 Human Spider", "number": 137, "color_identity": "G", "cost": "{1}{G}", "rules_text": "Reach\n{T}: You may put a land card from your hand onto the battlefield tapped.", "flavor_text": "[i][/i]", "pt": "1/3", "special_text": "", "shape": "adventure", "set": "KDT", "loyalty": "", "artist": "Liew Yu Liang John", "card_name2": "Growing Web", "color2": "G", "type2": "Sorcery \u2013 Adventure", "cost2": "{2}{G}", "rules_text2": "Search your library for up to two Forest cards, reveal them, put them into your hand, then shuffle. [i](Then exile this card. You may cast the creature later.)[/i]", "flavor_text2": "[i][/i]", "pt2": "", "special_text2": "", "loyalty2": "", "artist2": "", "notes": "", "image_type": "jpg"}