{"card_name": "Shigane Troupe Leader", "color": "UG", "rarity": "uncommon", "type": "Creature \u2013 Human Ninja", "number": 225, "color_identity": "UG", "cost": "{3}{G}{U}", "rules_text": "Whenever a creature you control leaves the battlefield without dying, you may put a permanent card with lesser mana value from your hand onto the battlefield.", "flavor_text": "[i]\u201cGet moving, and don't stop until you reach Shigane territory. I'll draw our pursuers away.\u201d[/i]", "pt": "5/5", "special_text": "", "shape": "normal", "set": "KDT", "loyalty": "", "artist": "SIXMOREVODKA", "notes": "", "image_type": "jpg"}