{"card_name": "Shadecrawler", "color": "B", "rarity": "uncommon", "type": "Creature \u2013 Nightmare Fungus Insect", "number": 101, "color_identity": "B", "cost": "{2}{B}", "rules_text": "Menace\nWhenever another creature you control dies, put a +1/+1 counter on this creature.", "flavor_text": "[i]The infection spreads through those who live, and die, in the Dreadmold.[/i]", "pt": "2/2", "special_text": "", "shape": "normal", "set": "AUR", "loyalty": "", "artist": "von-milano", "notes": "", "image_type": "jpg"}