{"card_name": "Hellfire Maw", "color": "BR", "rarity": "uncommon", "type": "Creature \u2013 Demon Beast", "number": 205, "color_identity": "BR", "cost": "{2}{B}{R}", "rules_text": "Aurora [i](At your end step, this may exile a noncreature from your graveyard into your aurora. Each grants up to one of its colors.)[/i]\nAs long as your aurora has three or more colors, this creature has menace. As long as it has five or more colors, it has double strike.", "flavor_text": "[i][/i]", "pt": "4/4", "special_text": "", "shape": "normal", "set": "AUR", "loyalty": "", "artist": "brent-hollowell", "notes": "!tokentag Aurora Reminder", "image_type": "jpg"}