{"card_name": "Icicle Tromper", "color": "U", "rarity": "uncommon", "type": "Creature \u2013 Ox", "number": 53, "color_identity": "U", "cost": "{4}{U}", "rules_text": "Ward {3}\nWhen this creature enters, tap up to one target creature and put a stun counter on it.", "flavor_text": "[i]\u201cThe area of cold around Areskarn's peak is almost perfectly a circle. My hypothesis is that something's up there.\u201d\n\u2014Vali, to Simul[/i]", "pt": "4/4", "special_text": "", "shape": "normal", "set": "AUR", "loyalty": "", "artist": "nube", "notes": "", "image_type": "jpg"}