{"card_name": "Wishtouched Outcast", "color": "B", "rarity": "rare", "type": "Creature \u2013 Vampire Wizard", "number": 109, "color_identity": "B", "cost": "{2}{B}", "rules_text": "Lifelink, menace\nAt the beginning of your upkeep, you may pursue Wonder. When you do, you lose life equal to the mana value of the card revealed this way. [i](To pursue Wonder, reveal a basic land or Wonder card you own from outside the game and put it into your hand.)[/i]", "flavor_text": "[i][/i]", "pt": "2/3", "special_text": "", "shape": "normal", "set": "WAW", "loyalty": "", "artist": "Corey Mcgill", "notes": "", "image_type": "jpg"}