{"card_name": "Weaving Reality in a Tapestry", "color": "G", "rarity": "common", "type": "Sorcery", "number": 170, "color_identity": "WUBRG", "cost": "{G}", "rules_text": "Search your library for a basic land card, reveal it, put it into your hand, then shuffle.\n[i]Augmented[/i] \u2013 If you've spent {W}{U}{B}{R}{G} to cast spells this turn, put four +1/+1 counters on up to one target creature you control.", "flavor_text": "[i]\u201cWhat was this plane before the Wonderlands?\u201d\n\u2014Fieldbook of Manuela Martinez[/i]", "pt": "", "special_text": "", "shape": "normal", "set": "WAW", "loyalty": "", "artist": "Kirinkarwai", "notes": "", "image_type": "jpg"}