{"card_name": "Starsea Bloomqueen", "color": "U", "rarity": "uncommon", "type": "Creature \u2013 Jellyfish", "number": 70, "color_identity": "UBR", "cost": "{4}{U}{U}", "rules_text": "Flying\n{1}{R}, Discard Starsea Bloomqueen: Starsea Bloomqueen deals 2 damage to any target.\n{6}{B}: You may exile six target cards from among graveyards. If you do, return Starsea Bloomqueen from your graveyard to the battlefield tapped.", "flavor_text": "[i][/i]", "pt": "5/6", "special_text": "", "shape": "normal", "set": "WAW", "loyalty": "", "artist": "Margot Zussy", "notes": "", "image_type": "jpg"}