{"card_name": "Velour, the Ragged King", "color": "WBR", "rarity": "uncommon", "type": "Legendary Creature \u2013 Human Pirate", "number": 115, "color_identity": "WBR", "cost": "{R}{W}{B}", "rules_text": "Haste\nPirates and Vehicles you control have \u201cWard\u2013{1}, Pay 1 life\u201d.\nWhenever a creature blocks a Pirate or Vehicle you control, if Velour is attacking, that creature gets -1/-1 until end of turn unless its controller pays {1} and 1 life.", "flavor_text": "[i][/i]", "pt": "4/2", "special_text": "", "shape": "normal", "set": "INK", "loyalty": "", "artist": "Created with MidjourneyAI", "notes": "", "image_type": "jpg"}