{"card_name": "Terraformer's Monument", "color": "", "rarity": "uncommon", "type": "Artifact", "number": 126, "color_identity": "C", "cost": "{4}", "rules_text": "Whenever you cast a spell, note one of that spell's colors that hasn't been noted by Terraformer's Monument. When you do, you gain 2 life.\nWhen five colors have been noted by Terraformer's Monument, sacrifice it. When you do, target player loses 10 life.", "flavor_text": "[i][/i]", "pt": "", "special_text": "", "shape": "normal", "set": "INK", "loyalty": "", "artist": "William Smith", "notes": "", "image_type": "jpg"}