{"card_name": "Kyouko Kasodani", "color": "R", "rarity": "common", "type": "Legendary Creature \u2013 Youkai Monk", "number": 109, "color_identity": "R", "cost": "{R}", "rules_text": "Echo {R} [i](At the beginning of your upkeep, if this came under your control since the beginning of your last upkeep, sacrifice it unless you pay its echo cost.)[/i]\nWhenever Kyouko enters or its echo cost is paid, target creature can't block this turn.", "flavor_text": "[i]\u201cGOOD MORNING, MISTER!\u201d[/i]", "pt": "2/2", "special_text": "", "shape": "normal", "set": "2HU", "loyalty": "", "artist": "\u751c\u74dc\u5f10\u3005/MELON22", "notes": "!tag TD\n!tag Kyouko\n!tag Kyoko\n!tag Myouren\n!tag Stage2", "image_type": "png"}