{"card_name": "Rinnosuke Morichika", "color": "U", "rarity": "uncommon", "type": "Legendary Creature \u2013 Human Youkai", "number": 62, "color_identity": "U", "cost": "{2}{U}", "rules_text": "Defender\nWhenever an artifact you control enters, you may scry X, where X is that artifact's mana value.", "flavor_text": "[i]\u201cEven though there's hardly a shop owner more unsuited to business, Kourindou is still the only shop that deals in items from the outside world, and because of this, it has its regulars.\u201d\n\u2014Hieda no Akyuu, [/i]The Gensokyo Chronicle[i][/i]", "pt": "1/4", "special_text": "", "shape": "normal", "set": "2HU", "loyalty": "", "artist": "\u4f1a\u5e06/ehokun", "notes": "!tag CoLA\n!tag Rinnosuke\n!tag Print", "image_type": "png"}