{"card_name": "Pomguard Squad", "color": "W", "rarity": "uncommon", "type": "Creature \u2013 Moogle", "number": 21, "color_identity": "W", "cost": "{4}{W}", "rules_text": "This creature gets +1/+1 and can block an additional creature each combat for each token you control.\nWhenever you cycle or discard a card, create a Map token. [i](It has \u201c{1}, {T}, Sacrifice this artifact: Target creature you control explores. Activate only as a sorcery.\u201d)[/i]", "flavor_text": "[i][/i]", "pt": "4/4", "special_text": "", "shape": "normal", "set": "EOR", "loyalty": "", "artist": "Square Enix", "notes": "", "image_type": "jpg"}