{"card_name": "Manacutter", "color": "", "rarity": "rare", "type": "Artifact \u2013 Vehicle", "number": 220, "color_identity": "C", "cost": "{2}", "rules_text": "Flying, double strike\nWhenever you cycle or discard a card, this artifact becomes an artifact creature until end of turn. It explores.\nCrew 1 [i](Tap any number of creatures you control with total power 1 or more: This Vehicle becomes an artifact creature until end of turn.)[/i]", "flavor_text": "[i][/i]", "pt": "1/2", "special_text": "", "shape": "normal", "set": "EOR", "loyalty": "", "artist": "Square Enix", "notes": "", "image_type": "jpg"}