{"card_name": "Legion Potentate", "color": "B", "rarity": "rare", "type": "Artifact Creature \u2013 Cyborg Soldier Knight", "number": 102, "color_identity": "B", "cost": "{2}{B}{B}", "rules_text": "Whenever this creature enters or attacks, you may search your library for a black creature card with mana value 2 or less, exile it, and shuffle. You may cast the exiled card by paying life equal to its mana value rather than paying its mana cost if that spell's mana value is 2 or less.", "flavor_text": "[i][/i]", "pt": "3/3", "special_text": "", "shape": "normal", "set": "SOV", "loyalty": "", "artist": "Alejandro Burdisio", "notes": "RB02,Small Creature,2,,Osteomancer Adept", "image_type": "jpg"}