{"card_name": "Tunnel-Hunter Griff", "color": "R", "rarity": "uncommon", "type": "Creature \u2013 Griffin Mutant", "number": 154, "color_identity": "R", "cost": "{3}{R}", "rules_text": "Haste\nWhenever you sacrifice a permanent, target creature can't block this turn.", "flavor_text": "[i]These griffs have adapted their wingspan for underground life. They have been the end of many a core expedition. [/i]", "pt": "4/3", "special_text": "", "shape": "normal", "set": "SOV", "loyalty": "", "artist": "Travis Anderson", "notes": "UR05,Medium Creature,4,,Brambleguard Captain", "image_type": "jpg"}