{"card_name": "Mutalist Vizier", "color": "G", "rarity": "common", "type": "Creature \u2013 Elf Mutant Druid", "number": 172, "color_identity": "G", "cost": "{2}{G}", "rules_text": "Whenever this creature attacks while you control a creature with power 4 or greater, it gets +2/+1 and gains trample until end of turn.", "flavor_text": "[i]Fed on rotten Leygrid mana, only the most resilient or profane things retain their shape.[/i]", "pt": "2/3", "special_text": "", "shape": "normal", "set": "SOV", "loyalty": "", "artist": "Alexey Kruglov", "notes": "CG07,Medium Creature,4,,Rust-Shield Rampager", "image_type": "jpg"}