{"card_name": "Failed Gateway", "color": "B", "rarity": "uncommon", "type": "Sorcery", "number": 100, "color_identity": "B", "cost": "{1}{B}{B}", "rules_text": "[i]Corrupt[/i] \u2013 All creatures get -2/-2 until end of turn. If you control a permanent with mana value 4 or greater, instead creatures your opponents control get -2/-2 until end of turn.", "flavor_text": "[i][/i]", "pt": "", "special_text": "", "shape": "normal", "set": "ERR", "loyalty": "", "artist": "Cotnonekot", "notes": "!tokens Program B EIW\nart4\n\nSwap with failed gateway (for black corrupt infest, red corrupt Subroutine of some kind) Hordeling Outburst?", "image_type": "jpg"}