{"card_name": "Helen's Failsafe", "color": "", "rarity": "uncommon", "type": "Artifact Creature \u2013 Construct", "number": 239, "color_identity": "", "cost": "{9}", "rules_text": "Ward {2} [i](Whenever this creature becomes the target of a spell or ability an opponent controls, counter it unless that player pays {2}.)[/i]\nWhenever this creature attacks, destroy up to one target nonland permanent.", "flavor_text": "[i]The Weft's founder didn't live long enough to enter it.[/i]", "pt": "12/10", "special_text": "", "shape": "normal", "set": "ERR", "loyalty": "", "artist": "Jeppe Mygh", "notes": "art2\n\nHo\u00e0ng L\u1eadp\n\nflagged (maybe)", "image_type": "jpg"}