{"card_name": "Student of Immortality", "color": "W", "rarity": "uncommon", "type": "Creature \u2013 Human Citizen", "number": 36, "color_identity": "W", "cost": "{2}{W}", "rules_text": "", "flavor_text": "[i][/i]", "pt": "4/2", "special_text": "Level up {1}{B} [i]({1}{B}: Put a level counter on this. Level up only as a sorcery.)[/i] [4/2]\n[level 1-3] When this creature dies, return it to its owner's hand. [5/3]\n[level 4+] Whenever a creature you control dies, return it its owner's hand. [6/4]", "shape": "leveler", "set": "ERR", "loyalty": "", "artist": "Macarious", "notes": "!tokens Memory EIW\ntype C\nart3", "image_type": "jpg"}