{"card_name": "Natural Tutor", "color": "G", "rarity": "uncommon", "type": "Sorcery", "number": 204, "color_identity": "G", "cost": "{1}{G}", "rules_text": "As an additional cost to cast this spell, discard a creature card or sacrifice a creature.\nSearch your library for a creature card, reveal it, put it into your hand, then shuffle.", "flavor_text": "[i][/i]", "pt": "", "special_text": "", "shape": "normal", "set": "PBA", "loyalty": "", "artist": "Pigsomedom", "notes": "", "image_type": "png"}