{"card_name": "Odayaka, Life's Tenacity", "color": "G", "rarity": "rare", "type": "Legendary Creature \u2013 Spirit God", "number": 159, "color_identity": "G", "cost": "{2}{G}", "rules_text": "Creatures you control have \u201c{T}: Add one mana of any color.\u201d\nWhenever you cast a spell, if four or more mana from nonland sources was spent to cast it, you may cast a copy of Odayaka's back face without paying it's mana cost. X equals the amount of mana from nonland sources spent to cast that spell.", "flavor_text": "[i][/i]", "pt": "1/4", "special_text": "", "shape": "modal double faced", "set": "ONI", "loyalty": "", "artist": "The Horse.", "card_name2": "Odayaka's Exertion", "color2": "G", "type2": "Sorcery", "cost2": "{X}{G}{G}", "rules_text2": "Search your library for a creature card with mana value X or less, put it onto the battlefield, then shuffle.", "flavor_text2": "[i]Odayaka represents selfless nurturing, and believes in the growth in all things.[/i]", "pt2": "", "special_text2": "", "loyalty2": "", "artist2": "Ekokuron", "notes": "", "image_type": "jpg"}