{"card_name": "Backstage Film Crew", "color": "WUR", "rarity": "uncommon", "type": "Creature \u2013 Dog Fox Rabbit Spirit", "number": 185, "color_identity": "WUR", "cost": "{2}{U}{R}{W}", "rules_text": "Double strike\nWhenever a creature you control with base power 2 or less attacks, reveal the top card of your library. Put it onto the battlefield tapped and attacking if it's creature with base power 2 or less. Otherwise, you may put it on the bottom of your library.", "flavor_text": "[i][/i]", "pt": "2/4", "special_text": "", "shape": "normal", "set": "ONI", "loyalty": "", "artist": "sanshouuo", "notes": "", "image_type": "jpg"}