{"card_name": "Hollow Confluence", "color": "WBR", "rarity": "rare", "type": "Sorcery", "number": 206, "color_identity": "WBR", "cost": "{2}{R}{W}{B}", "rules_text": "Choose three. You may choose the same mode more than once.\n\u2022 Create a token that's a copy of target creature you control, except it has haste. Sacrifice it at the beginning of your next end step.\n\u2022 You gain 2 life for each creature you control.\n\u2022 Each player sacrifices a nontoken creature.", "flavor_text": "[i][/i]", "pt": "", "special_text": "", "shape": "normal", "set": "ONI", "loyalty": "", "artist": "Meka Aoratos", "notes": "", "image_type": "jpg"}