{"card_name": "True Blood", "color": "B", "rarity": "common", "type": "Sorcery", "number": 129, "color_identity": "BR", "cost": "{B}", "rules_text": "Create a 1/1 black and red Vampire creature token with menace. If this spell was cast from a graveyard, create two of those tokens instead.\nFlashback {3}{R} [i](You may cast this card from your graveyard for its flashback cost. Then exile it.)[/i]", "flavor_text": "[i][/i]", "pt": "", "special_text": "", "shape": "normal", "set": "INM", "loyalty": "", "artist": "Marcela Medeiros", "notes": "", "image_type": "jpg"}