{"card_name": "Obsidian Hellkite", "color": "R", "rarity": "uncommon", "type": "Creature \u2013 Dragon", "number": 163, "color_identity": "R", "cost": "{3}{R}", "rules_text": "Foreshadow {4}{R}{R} [i](You may cast this spell for its foreshadow cost. If you do, also trigger its \u201cdies\u201d ability when it enters.)[/i]\nFlying\nWhen Obsidian Hellkite dies, it deals 2 damage to up to one target creature or planeswalker. If that creature or planeswalker would die this turn, exile it instead.", "flavor_text": "[i][/i]", "pt": "3/2", "special_text": "", "shape": "normal", "set": "INM", "loyalty": "", "artist": "Anato Finnstark", "notes": "", "image_type": "jpg"}