{"card_name": "Krallenmaw, the Tempter", "color": "BG", "rarity": "rare", "type": "Legendary Creature \u2013 Demon", "number": 237, "color_identity": "BG", "cost": "{3}{B}{G}", "rules_text": "Menace\nYou may spend mana as though it were mana of any color to cast double-faced spells or activate abilities of double-faced sources.\nOnce during each of your turns, you may cast a double-faced spell you own from outside the game.", "flavor_text": "[i][/i]", "pt": "6/6", "special_text": "", "shape": "normal", "set": "INM", "loyalty": "", "artist": "Cosme Lucero", "notes": "", "image_type": "jpg"}