{"card_name": "Breaking Dawn", "color": "W", "rarity": "common", "type": "Instant", "number": 9, "color_identity": "W", "cost": "{2}{W}", "rules_text": "Choose one \u2013\n\u2022 Creatures you control get +2/+0 until end of turn.\n\u2022 Destroy target artifact or enchantment. You gain 3 life.", "flavor_text": "[i]\u201cOnly if the day comes can night return.\u201d \u2014Sorin Markov[/i]", "pt": "", "special_text": "", "shape": "normal", "set": "INM", "loyalty": "", "artist": "Josh Hass", "notes": "", "image_type": "jpg"}