{"card_name": "Merry Marauder", "color": "R", "rarity": "common", "type": "Creature \u2013 Elf Soldier", "number": 133, "color_identity": "R", "cost": "{1}{R}", "rules_text": "Deception {R} [i]({R}, Return an unblocked attacker you control to hand: Put this card onto the battlefield from your hand tapped and attacking.)[/i]\nWhen this creature enters, create a tapped Treasure token if you don't control a Treasure.", "flavor_text": "[i][/i]", "pt": "2/2", "special_text": "", "shape": "normal", "set": "MSK", "loyalty": "", "artist": "Zuzanna Wuzyk", "notes": "Warkrei", "image_type": "jpg"}