{"card_name": "Disinherited Scion", "color": "W", "rarity": "uncommon", "type": "Creature \u2013 Elf Noble", "number": 8, "color_identity": "W", "cost": "{1}{W}", "rules_text": "Boast\u2013Discard a card: This creature gains indestructible until end of turn. [i](Activate only if this creature attacked this turn and only once each turn.)[/i]", "flavor_text": "[i]Adventurous civilians see opportunity behind the Warkrei advance: new lands to claim, and with it, new titles to earn.[/i]", "pt": "3/1", "special_text": "", "shape": "normal", "set": "MSK", "loyalty": "", "artist": "Zuzanna Wuzyk", "notes": "Warkrei", "image_type": "jpg"}