{"card_name": "Lost Sanctuary", "color": "G", "rarity": "common", "type": "Enchantment", "number": 137, "color_identity": "G", "cost": "{G}", "rules_text": "When Lost Sanctuary enters, search your library for a basic land card, put it into your hand, then shuffle.\nWhenever you cast a spell with attune, you may sacrifice Lost Sanctuary. If you do, you gain 3 life.", "flavor_text": "[i][/i]", "pt": "", "special_text": "", "shape": "normal", "set": "SHS", "loyalty": "", "artist": "Ryky", "notes": "", "image_type": "jpg"}