{"card_name": "Marraq", "color": "", "rarity": "uncommon", "type": "Land \u2013 Desert", "number": 200, "color_identity": "C", "cost": "", "rules_text": "{T}: Add {C}.\n{1}, {T}, Sacrifice Marraq: Create a 1/1 Ally creature token that's all colors.", "flavor_text": "[i]In war, trading hubs not only control the flow of goods but also the flow of soldiers.[/i]", "pt": "", "special_text": "", "shape": "normal", "set": "SHS", "loyalty": "", "artist": "Alexander Forssberg", "notes": "", "image_type": "jpg"}