{"card_name": "Endless Breakthroughs", "color": "U", "rarity": "rare", "type": "Instant", "number": 12, "color_identity": "U", "cost": "{3}{U}{U}", "rules_text": "You may discard your hand. If you discarded at least three cards this way, draw five cards.\nYou may sacrifice a land. If you do, copy Endless Breakthroughs.", "flavor_text": "[i]\u201cWait, no, but that means...aha! And then of course...\u201d[/i]", "pt": "", "special_text": "", "shape": "normal", "set": "PTXX", "loyalty": "", "artist": "Donato Giancola", "notes": "!tag Akieva\n!tag Endless Ambition Combo", "image_type": "jpg"}