{"card_name": "Learn from Dragons", "color": "R", "rarity": "uncommon", "type": "Sorcery", "number": 43, "color_identity": "R", "cost": "{R}", "rules_text": "Target creature gains trample until end of turn.\nTarget creature gains haste until end of turn.\nTarget creature gains first strike until end of turn.\nDraw a card.", "flavor_text": "[i][/i]", "pt": "", "special_text": "", "shape": "normal", "set": "PTXX", "loyalty": "", "artist": "Anna Podedworna", "notes": "!tag Fangs\n!tag Wizard Burn", "image_type": "jpg"}