{"card_name": "Firmament Sculptor", "color": "U", "rarity": "rare", "type": "Artifact Creature \u2013 Avatar", "number": 48, "color_identity": "U", "cost": "{1}{U}", "rules_text": "Impending 3\u2013{4}{U} [i](If this spell was impending, it enters with three time counters and isn't a creature until they're removed. At the beginning of your end step, remove one.)[/i]\nFlying\nWhenever a time counter is removed from Firmament Sculptor, create a token copy of it.", "flavor_text": "[i][/i]", "pt": "2/1", "special_text": "", "shape": "normal", "set": "ITD", "loyalty": "", "artist": "Aldo Katayanagi", "notes": "", "image_type": "jpg"}