{"card_name": "The Eternal Echo", "color": "", "rarity": "rare", "type": "Legendary Planeswalker \u2013 Echo", "number": 4, "color_identity": "C", "cost": "{4}", "rules_text": "", "flavor_text": "[i][/i]", "pt": "", "special_text": "Whenever you activate a loyalty ability of The Eternal Echo, create a colorless Echo planeswalker token at the beginning of your next end step and put 3 loyalty counters on it. It gains that ability, except it costs [-1].\n[+1]: You gain 2 life.\n[+0]: Put a +1/+1 counter on target creature you control. \n[-2]: Each opponent loses 2 life.\n[-5]: Draw a card.", "shape": "planeswalker", "set": "ITD", "loyalty": "3", "artist": "Huleeb", "notes": "", "image_type": "jpg"}